dr14meter/__init__.py
dr14meter/__main__.py
dr14meter/audio_analysis.py
dr14meter/audio_decoder.py
dr14meter/audio_file_reader.py
dr14meter/audio_math.py
dr14meter/audio_track.py
dr14meter/compressor.py
dr14meter/compute_dr.py
dr14meter/compute_dr14.py
dr14meter/compute_drv.py
dr14meter/dr14_config.py
dr14meter/dr14_global.py
dr14meter/dr14_tmeter.py
dr14meter/dr14_utils.py
dr14meter/duration.py
dr14meter/dynamic_range_meter.py
dr14meter/out_messages.py
dr14meter/parse_args.py
dr14meter/read_metadata.py
dr14meter/table.py
dr14meter/tagger.py
dr14meter/wav_write.py
dr14meter/write_dr.py
dr14meter/database/__init__.py
dr14meter/database/database.py
dr14meter/database/database_utils.py
dr14meter/database/query.py
dr14meter/plot/__init__.py
dr14meter/plot/dr_histogram.py
dr14meter/plot/dynamic_vivacity.py
dr14meter/plot/lev_histogram.py
dr14meter/plot/my_time_formatter.py
dr14meter/plot/plot_track.py
dr14meter/plot/plot_track_classic.py
dr14meter/plot/spectrogram.py
dr14meter-1.1.3.dist-info/LICENSE
dr14meter-1.1.3.dist-info/METADATA
dr14meter-1.1.3.dist-info/WHEEL
dr14meter-1.1.3.dist-info/entry_points.txt
dr14meter-1.1.3.dist-info/top_level.txt
dr14meter-1.1.3.dist-info/RECORD
