Metadata-Version: 2.2
Name: dr14meter
Version: 1.1.3
Summary: Compute the dynamic range DR14 value of the given audio files
Author-email: pe7ro <44572319+pe7ro@users.noreply.github.com>
License: GPL-3.0+
Project-URL: Homepage, https://github.com/pe7ro/dr14meter
Project-URL: Bug Reports, https://github.com/pe7ro/dr14meter/issues
Project-URL: Source, https://github.com/pe7ro/dr14meter
Keywords: dr14,dynamic range,loudness war
Classifier: Development Status :: 5 - Production/Stable
Classifier: Environment :: Console
Classifier: Intended Audience :: End Users/Desktop
Classifier: License :: OSI Approved :: GNU General Public License v3 or later (GPLv3+)
Classifier: Operating System :: POSIX :: Linux
Classifier: Programming Language :: Python
Classifier: Programming Language :: Python :: 3
Classifier: Programming Language :: Python :: 3.12
Classifier: Topic :: Multimedia :: Sound/Audio :: Analysis
Requires-Python: >=3.4
License-File: LICENSE
Requires-Dist: numpy
Requires-Dist: mutagen
Provides-Extra: plot
Requires-Dist: matplotlib>=2; extra == "plot"
Requires-Dist: scipy; extra == "plot"
